{
    "file_path": "C:/Users/mattc/Desktop/TFG - Gestor Energetic/sim/db/2022-06-06..2022-06-11 Jordi.csv",
    "start_date": "2022-06-10 04:00",
    "end_date": "2022-06-10 19:00",
    "algorithm": "Time To Consume",
    "predict_final_energy": "Project Current Power",
    "subdivide_eb": "Level 2",
    "subdivide_t": "Level 2",
    "op_setting": "End at [Wh]",
    "op_ax_right": "Daily Commutations",
    "op_ax_left": "Cons. Max. Efficiency [%]",
    "show_max_cons": "Hide",
    "mot_mode": "2n on if 1st on",
    "th_top1": 83,
    "th_top2": 166,
    "th_bottom1": -10,
    "th_bottom2": 0,
    "time_limit": 600,
    "base_load": 100,
    "load1": 500,
    "load2": 500,
    "ttc_end_at": 10,
    "ttc_on_min": 150,
    "op_start": 240.0,
    "op_end": 600.0,
    "op_step": 20.0,
    "ttc_time_factor": 0.8,
    "sell_price": 0.187,
    "generation_factor": 0.9999999999999999,
    "use_data_bl": false,
    "show_loads_area": true,
    "show_th": true,
    "energyP_s": false,
    "show_values_eb": false,
    "show_ecm_eb": false,
    "show_values_effC": true,
    "show_values_effGR": true,
    "show_values_balance": true,
    "show_values_commut": true,
    "show_values_t": true,
    "show_ecm_t": false,
    "data_line_style": "-",
    "sim_line_style": "-",
    "table_price_energy": [
        0.241,
        0.241,
        0.241,
        0.241,
        0.241,
        0.241,
        0.241,
        0.241,
        0.293,
        0.293,
        0.357,
        0.357,
        0.357,
        0.357,
        0.293,
        0.293,
        0.293,
        0.293,
        0.357,
        0.357,
        0.357,
        0.357,
        0.293,
        0.293
    ]
}